{"Dark Wood Fafnir": [0, 0, 100, 100], "Fertility Deity, Evil Ceres": [0, 100, 100, 200], "Astaroth": [0, 200, 100, 300], "Wind Archdemon Astaroth": [0, 300, 100, 400], "Noble Wolf King Hero, Cu Chulainn": [0, 400, 100, 500], "Green Stone Dragon, Adamant": [0, 500, 100, 600], "Jade Dragon Caller, Sonia": [0, 600, 100, 700], "Eternal Jade Dragon Caller, Sonia": [0, 700, 100, 800], "Awoken Hera-Beorc": [0, 800, 100, 900], "Pure Demon Lord, Astaroth": [0, 900, 100, 1000], "Underworld Protector Genbu, Meimei": [0, 1000, 100, 1100], "Genius Sleeping Dragon, Zhuge Liang": [0, 1100, 100, 1200], "Namekian, Piccolo": [100, 0, 200, 100], "Awoken Black Dios": [100, 100, 200, 200], "Thorned Guardian, Graceful Valkyrie": [100, 200, 200, 300], "Cell - Complete Form": [100, 300, 200, 400], "Moonlit Feline Goddess, Bastet": [100, 400, 200, 500], "Chivalric Demon Prince, Cauchemar": [100, 500, 200, 600], "ABE Royal Guard Pig": [100, 600, 200, 700], "Ultimate Lifeform, Doomsday (Comics)": [100, 700, 200, 800], "genius sleeping dragon, zhuge liang": [100, 800, 200, 900], "Thorned Goddess, Valkyrie Elize": [100, 900, 200, 1000], "Green Angel, Ruel": [100, 1000, 200, 1100], "Green-Winged Star Angel, Ruel": [100, 1100, 200, 1200], "Crystal Wind Dragon Queen, Linthia": [200, 0, 300, 100], "Nanto Kokakuken Master, Juda": [200, 100, 300, 200], "Final Equip, Thief": [200, 200, 300, 300], "Perfect Cell": [200, 300, 300, 400], "Dimensional Travelers, Aemo & Mootie": [200, 400, 300, 500], "Cloud of Darkness": [200, 500, 300, 600], "Griffin Rider": [200, 600, 300, 700], "Griffin Rider, Gilliam": [200, 700, 300, 800], "Relentless Destroyer, Grand Tengu": [200, 800, 300, 900], "Awoken Black Dios Stratios": [200, 900, 300, 1000], "Moon Flower Huntress, Artemis": [200, 1000, 300, 1100], "Diligent Spy, Ishida Mitsunari": [200, 1100, 300, 1200], "Combat State, Armored Titan": [300, 0, 400, 100], "Awoken Freyja": [300, 100, 400, 200], "Dark Plant Mechanical Star God, Spica": [300, 200, 400, 300], "Demon Destroying Star Angel, Ruel": [300, 300, 400, 400], "Past Life Jade Dragon Caller, Sonia": [300, 400, 400, 500], "Anti-God Machine, Ragnarok Dragon": [300, 500, 400, 600], "P.A.D Leader, Haruyama Koichi": [300, 600, 400, 700], "Jade Jewel Princess, Cameo": [300, 700, 400, 800], "Former R&D Chief, Kisuke Urahara": [300, 800, 400, 900], "Rainbow Wing Whirlwind Dragon Emperor, Sevenzard": [300, 900, 400, 1000], "Gabranth": [300, 1000, 400, 1100], "Colorful Queen, Hera-Beorc": [300, 1100, 400, 1200], "Library Room's Manager God, Kali": [400, 0, 500, 100], "Focalor Djinn Equip, Sinbad": [400, 100, 500, 200], "Zagan Djinn Equip, Ren Hakuryuu": [400, 200, 500, 300], "Loyal Demon Prince, Cauchemar": [400, 300, 500, 400], "Bastet Armor X Dragon Caller, Ace": [400, 400, 500, 500], "Juppongatana \"The Scythe\", Honjo Kamatari": [400, 500, 500, 600], "Spirit Tree Mechanical Star God, Spica": [400, 600, 500, 700], "Tyrannical Spy, Ishida Mitsunari": [400, 700, 500, 800], "Masquerade Goddess, Parvati": [400, 800, 500, 900], "Masquerade Rock Singer, Misery": [400, 900, 500, 1000], "Reincarnated Ceres": [400, 1000, 500, 1100], "Daughter of the Hell Phantom Demon, Romia": [400, 1100, 500, 1200], "Reincarnated Susano no Mikoto": [500, 0, 600, 100], "Soul Reclaimer God of Dark Riches, Osiris": [500, 100, 600, 200], "Reincarnated Meimei": [500, 200, 600, 300], "Reincarnated Astaroth": [500, 300, 600, 400], "Awoken Perseus": [500, 400, 600, 500], "Inquisitive Hell Phantom Heiress, Romia": [500, 500, 600, 600], "Awoken Vishnu": [500, 600, 600, 700], "Master Librarian Goddess, Kali": [500, 700, 600, 800], "Massacre Demon Diablos": [500, 800, 600, 900], "Awoken Oichi": [500, 900, 600, 1000], "Male Hunter, Demon X Gear": [500, 1000, 600, 1100], "Quartz Cipher Dragon Caller, Ney": [500, 1100, 600, 1200], "Destructive Machine God, Ragnarok Dragon": [600, 0, 700, 100], "Awoken Ishida Mitsunari": [600, 100, 700, 200], "Parademon Brawler (Film)": [600, 200, 700, 300], "Mastermind of Revenge, Yukishiro Enishi": [600, 300, 700, 400], "Ling Yao": [600, 400, 700, 500], "Envy": [600, 500, 700, 600], "Ivanus": [600, 600, 700, 700], "Composed God of Great Knowledge, Dagda": [600, 700, 700, 800], "Valentine Cymophane Princess, Sheen": [600, 800, 700, 900], "Mega Awoken Green Dragon Caller, Sonia Fio": [600, 900, 700, 1000], "Tatsuo Kuzugami": [600, 1000, 700, 1100], "Yoko Kurama": [600, 1100, 700, 1200], "Warbeast God of Loyalty, Enkidu": [700, 0, 800, 100], "Vraska": [700, 100, 800, 200], "Vraska the Unseen": [700, 200, 800, 300], "Vraska Premium Card": [700, 300, 800, 400], "SO135-Alastair": [700, 400, 800, 500], "Toushirou Hijikata": [700, 500, 800, 600], "Toushirou Hijikata in Liu Bei Costume": [700, 600, 800, 700], "Black Scissors Cutting Dragon Caller, Roche": [700, 700, 800, 800], "Five Virtues' One-Eyed God, Date Masamune": [700, 800, 800, 900], "Manjimutt": [700, 900, 800, 1000], "Slimamander": [700, 1000, 800, 1100], "Servant, Assassin": [700, 1100, 800, 1200], "Itsuki": [800, 0, 900, 100], "Raizer (Dark Color)": [800, 100, 900, 200], "Silva": [800, 200, 900, 300], "Wise Draconic Songstress on Clarinet, Enola": [800, 300, 900, 400], "Luluna [Dark Color]": [800, 400, 900, 500], "Romia's Plushie": [800, 500, 900, 600], "Rebellious Crow Tengu, Yashamaru Kurama": [800, 600, 900, 700], "Zelgadis Greywords": [800, 700, 900, 800], "Shinobu Tsukiyama & E3 Tsubasa Iron Wing": [800, 800, 900, 900], "Miku Hatsune & H5 Hayabusa": [800, 900, 900, 1000], "Gaia The Fierce Knight": [800, 1000, 900, 1100], "Lilia [Dark Color]": [800, 1100, 900, 1200], "Super Reincarnated Freyja": [900, 0, 1000, 100], "Pixel Great Earl of Hell, Ronove": [900, 100, 1000, 200], "Reincarnated Odin Dragon": [900, 200, 1000, 300], "Roche Disguise": [900, 300, 1000, 400], "Freyja Disguise": [900, 400, 1000, 500], "Sonia Fio Disguise": [900, 500, 1000, 600], "Goofy (Happiness)": [900, 600, 1000, 700], "Oversleeping Cloud Dragon Caller, Erika": [900, 700, 1000, 800], "Super Reincarnated Astaroth": [900, 800, 1000, 900], "Healing Archangel, Raphael (Dark Color)": [900, 900, 1000, 1000], "Pixel Lively Maiden, Princess Valkyrie": [900, 1000, 1000, 1100], "Overhaul": [900, 1100, 1000, 1200], "Futaba Sakura": [1000, 0, 1100, 100], "Deadly Sin Dragon King of Sloth, Fegoran": [1000, 100, 1100, 200], "Sloth Evil Key": [1000, 200, 1100, 300], "Mighty Morphin Green Ranger": [1000, 300, 1100, 400]}